PyouPlay/__init__.py
PyouPlay/get.py
PyouPlay-0.1.data/scripts/get.py
PyouPlay-0.1.dist-info/METADATA
PyouPlay-0.1.dist-info/RECORD
PyouPlay-0.1.dist-info/WHEEL
PyouPlay-0.1.dist-info/top_level.txt
