Metadata-Version: 2.1
Name: PyouPlay
Version: 0.1
Summary: This is a simple python package when passed with a search argument returns link to video.
Home-page: https://github.com/omi10859/PyouPlay
Author: Omkar Yadav
Author-email: omkar10859@gmail.com
License: UNKNOWN
Platform: UNKNOWN
Requires-Dist: bs4 (>=0.0.1)
Requires-Dist: beautifulsoup4 (>=4.6.0)
Requires-Dist: requests (>=2.19.1)
Requires-Dist: urllib3 (>=1.23)
Requires-Dist: certifi (>=2018.4.16)
Requires-Dist: chardet (>=3.0.4)
Requires-Dist: lxml (>=4.2.3)
